{
  "version": "1.0.0",
  "generatedAt": "2026-07-11T22:45:08.603Z",
  "summary": {
    "surfaces": {
      "total": 26,
      "aligned": 26,
      "drift": 0
    },
    "actions": {
      "total": 38,
      "aligned": 38,
      "drift": 0
    },
    "orphanActions": [],
    "internalActions": [
      "action:adminSignInAction",
      "action:validateSurveyPackageAction"
    ]
  },
  "surfaces": [
    {
      "surfaceId": "client-join",
      "route": "/join",
      "mode": "source-scan",
      "compare": {
        "declared": [
          "auth:email-otp",
          "auth:organization/accept-invitation",
          "auth:sign-up/email",
          "domain:auth",
          "domain:client-invitation-entry"
        ],
        "discovered": [
          "domain:auth"
        ],
        "aligned": [
          "auth:email-otp",
          "auth:organization/accept-invitation",
          "auth:sign-up/email",
          "domain:auth",
          "domain:client-invitation-entry"
        ],
        "declaredOnly": [],
        "discoveredOnly": [],
        "inherited": [
          "auth:email-otp",
          "auth:organization/accept-invitation",
          "auth:sign-up/email",
          "domain:client-invitation-entry"
        ],
        "status": "aligned"
      },
      "evidence": {
        "entryFiles": [
          "app/join/page.tsx",
          "features/auth/studio-invitation-join-page.tsx",
          "features/auth/invitation-join-panel.tsx",
          "features/auth/invitation-join-steps.tsx",
          "features/auth/use-join-invitation-auth-view.ts",
          "modules/identity/client-invitation-join-auth.ts",
          "features/auth/entry/client-invitation-entry.ts"
        ],
        "scannedFiles": [
          "app/join/page.tsx",
          "features/auth/entry/client-invitation-entry.ts",
          "features/auth/invitation-join-panel.tsx",
          "features/auth/invitation-join-steps.tsx",
          "features/auth/studio-invitation-join-page.tsx",
          "features/auth/use-join-invitation-auth-view.ts",
          "modules/identity/client-invitation-join-auth.ts"
        ]
      }
    },
    {
      "surfaceId": "auth-sign-in",
      "route": "/auth/sign-in",
      "mode": "auth-pathname",
      "compare": {
        "declared": [
          "auth:sign-in/email"
        ],
        "discovered": [
          "auth:sign-in/email"
        ],
        "aligned": [
          "auth:sign-in/email"
        ],
        "declaredOnly": [],
        "discoveredOnly": [],
        "inherited": [],
        "status": "aligned"
      },
      "evidence": {
        "entryFiles": [
          "app/auth/[path]/page.tsx",
          "features/auth/entry/auth-view-entry.tsx",
          "features/auth/studio-auth-login-page.tsx",
          "features/auth/studio-auth-shell.tsx",
          "features/auth/auth-page-trust.ts"
        ],
        "scannedFiles": [
          "app/auth/[path]/page.tsx",
          "features/auth/auth-page-trust.ts",
          "features/auth/entry/auth-view-entry.tsx",
          "features/auth/studio-auth-login-page.tsx",
          "features/auth/studio-auth-shell.tsx"
        ]
      }
    },
    {
      "surfaceId": "auth-sign-up",
      "route": "/auth/sign-up",
      "mode": "auth-pathname",
      "compare": {
        "declared": [
          "auth:sign-up/email"
        ],
        "discovered": [
          "auth:sign-up/email"
        ],
        "aligned": [
          "auth:sign-up/email"
        ],
        "declaredOnly": [],
        "discoveredOnly": [],
        "inherited": [],
        "status": "aligned"
      },
      "evidence": {
        "entryFiles": [
          "app/auth/[path]/page.tsx",
          "features/auth/entry/auth-view-entry.tsx",
          "features/auth/studio-auth-login-page.tsx",
          "features/auth/auth-page-trust.ts"
        ],
        "scannedFiles": [
          "app/auth/[path]/page.tsx",
          "features/auth/auth-page-trust.ts",
          "features/auth/entry/auth-view-entry.tsx",
          "features/auth/studio-auth-login-page.tsx"
        ]
      }
    },
    {
      "surfaceId": "auth-email-otp",
      "route": "/auth/email-otp",
      "mode": "auth-pathname",
      "compare": {
        "declared": [
          "auth:email-otp"
        ],
        "discovered": [
          "auth:email-otp"
        ],
        "aligned": [
          "auth:email-otp"
        ],
        "declaredOnly": [],
        "discoveredOnly": [],
        "inherited": [],
        "status": "aligned"
      },
      "evidence": {
        "entryFiles": [
          "app/auth/[path]/page.tsx",
          "features/auth/entry/auth-view-entry.tsx",
          "features/auth/studio-auth-login-page.tsx",
          "features/auth/auth-page-trust.ts"
        ],
        "scannedFiles": [
          "app/auth/[path]/page.tsx",
          "features/auth/auth-page-trust.ts",
          "features/auth/entry/auth-view-entry.tsx",
          "features/auth/studio-auth-login-page.tsx"
        ]
      }
    },
    {
      "surfaceId": "auth-forgot-password",
      "route": "/auth/forgot-password",
      "mode": "auth-pathname",
      "compare": {
        "declared": [
          "auth:forget-password"
        ],
        "discovered": [
          "auth:forget-password"
        ],
        "aligned": [
          "auth:forget-password"
        ],
        "declaredOnly": [],
        "discoveredOnly": [],
        "inherited": [],
        "status": "aligned"
      },
      "evidence": {
        "entryFiles": [
          "app/auth/[path]/page.tsx",
          "features/auth/entry/auth-view-entry.tsx",
          "features/auth/studio-auth-login-page.tsx",
          "features/auth/auth-page-trust.ts"
        ],
        "scannedFiles": [
          "app/auth/[path]/page.tsx",
          "features/auth/auth-page-trust.ts",
          "features/auth/entry/auth-view-entry.tsx",
          "features/auth/studio-auth-login-page.tsx"
        ]
      }
    },
    {
      "surfaceId": "auth-reset-password",
      "route": "/auth/reset-password",
      "mode": "auth-pathname",
      "compare": {
        "declared": [
          "auth:reset-password"
        ],
        "discovered": [
          "auth:reset-password"
        ],
        "aligned": [
          "auth:reset-password"
        ],
        "declaredOnly": [],
        "discoveredOnly": [],
        "inherited": [],
        "status": "aligned"
      },
      "evidence": {
        "entryFiles": [
          "app/auth/[path]/page.tsx",
          "features/auth/entry/auth-view-entry.tsx",
          "features/auth/studio-auth-login-page.tsx",
          "features/auth/auth-page-trust.ts"
        ],
        "scannedFiles": [
          "app/auth/[path]/page.tsx",
          "features/auth/auth-page-trust.ts",
          "features/auth/entry/auth-view-entry.tsx",
          "features/auth/studio-auth-login-page.tsx"
        ]
      }
    },
    {
      "surfaceId": "auth-accept-invitation",
      "route": "/auth/accept-invitation",
      "mode": "source-scan",
      "compare": {
        "declared": [
          "auth:organization/accept-invitation",
          "domain:auth",
          "domain:client-invitation-entry"
        ],
        "discovered": [
          "domain:auth"
        ],
        "aligned": [
          "auth:organization/accept-invitation",
          "domain:auth",
          "domain:client-invitation-entry"
        ],
        "declaredOnly": [],
        "discoveredOnly": [],
        "inherited": [
          "auth:organization/accept-invitation",
          "domain:client-invitation-entry"
        ],
        "status": "aligned"
      },
      "evidence": {
        "entryFiles": [
          "app/auth/[path]/page.tsx",
          "features/auth/entry/auth-view-entry.tsx",
          "features/auth/studio-auth-login-page.tsx",
          "features/auth/entry/client-invitation-entry.ts"
        ],
        "scannedFiles": [
          "app/auth/[path]/page.tsx",
          "features/auth/entry/auth-view-entry.tsx",
          "features/auth/entry/client-invitation-entry.ts",
          "features/auth/studio-auth-login-page.tsx"
        ]
      }
    },
    {
      "surfaceId": "client-login",
      "route": "/client/login",
      "mode": "auth-pathname",
      "compare": {
        "declared": [
          "auth:sign-in/email"
        ],
        "discovered": [
          "auth:sign-in/email"
        ],
        "aligned": [
          "auth:sign-in/email"
        ],
        "declaredOnly": [],
        "discoveredOnly": [],
        "inherited": [],
        "status": "aligned"
      },
      "evidence": {
        "entryFiles": [
          "app/client/(gate)/login/page.tsx",
          "features/auth/entry/client-sign-in-entry.ts",
          "modules/platform/routing/portal-routes.ts"
        ],
        "scannedFiles": [
          "app/client/(gate)/login/page.tsx",
          "features/auth/entry/client-sign-in-entry.ts",
          "modules/platform/routing/portal-routes.ts"
        ]
      }
    },
    {
      "surfaceId": "client-home-redirect",
      "route": "/",
      "mode": "source-scan",
      "compare": {
        "declared": [
          "auth:sign-in/email",
          "domain:auth",
          "domain:client-invitation-entry"
        ],
        "discovered": [
          "domain:auth"
        ],
        "aligned": [
          "auth:sign-in/email",
          "domain:auth",
          "domain:client-invitation-entry"
        ],
        "declaredOnly": [],
        "discoveredOnly": [],
        "inherited": [
          "auth:sign-in/email",
          "domain:client-invitation-entry"
        ],
        "status": "aligned"
      },
      "evidence": {
        "entryFiles": [
          "app/page.tsx",
          "features/auth/entry/client-home-entry.tsx",
          "features/landing/lynx-landing-page.tsx",
          "features/landing/vanguard-landing.tsx",
          "features/landing/ritual-engine.ts",
          "features/landing/lynx-landing.css",
          "public/lynx/lynx-laptop.png",
          "public/lynx/lynx-laptop.webp",
          "public/lynx/lynx-auth-popup.png",
          "features/auth/entry/client-sign-in-entry.ts",
          "features/auth/entry/client-invitation-entry.ts",
          "modules/platform/routing/portal-routes.ts"
        ],
        "scannedFiles": [
          "app/page.tsx",
          "features/auth/entry/client-home-entry.tsx",
          "features/auth/entry/client-invitation-entry.ts",
          "features/auth/entry/client-sign-in-entry.ts",
          "features/landing/lynx-landing-page.tsx",
          "features/landing/lynx-landing.css",
          "features/landing/ritual-engine.ts",
          "features/landing/vanguard-landing.tsx",
          "modules/platform/routing/portal-routes.ts",
          "public/lynx/lynx-auth-popup.png",
          "public/lynx/lynx-laptop.png",
          "public/lynx/lynx-laptop.webp"
        ]
      }
    },
    {
      "surfaceId": "client-preview-unavailable",
      "route": "/client/preview-unavailable",
      "mode": "source-scan",
      "compare": {
        "declared": [],
        "discovered": [],
        "aligned": [],
        "declaredOnly": [],
        "discoveredOnly": [],
        "inherited": [],
        "status": "aligned"
      },
      "evidence": {
        "entryFiles": [
          "app/client/(gate)/preview-unavailable/page.tsx",
          "modules/identity/preview-client.ts"
        ],
        "scannedFiles": [
          "app/client/(gate)/preview-unavailable/page.tsx",
          "modules/identity/preview-client.ts"
        ]
      }
    },
    {
      "surfaceId": "client-onboarding",
      "route": "/client/onboarding",
      "mode": "source-scan",
      "compare": {
        "declared": [],
        "discovered": [],
        "aligned": [],
        "declaredOnly": [],
        "discoveredOnly": [],
        "inherited": [],
        "status": "aligned"
      },
      "evidence": {
        "entryFiles": [
          "app/client/(workspace)/onboarding/page.tsx"
        ],
        "scannedFiles": [
          "app/client/(workspace)/onboarding/page.tsx"
        ]
      }
    },
    {
      "surfaceId": "client-profile",
      "route": "/client/profile",
      "mode": "source-scan",
      "compare": {
        "declared": [],
        "discovered": [],
        "aligned": [],
        "declaredOnly": [],
        "discoveredOnly": [],
        "inherited": [],
        "status": "aligned"
      },
      "evidence": {
        "entryFiles": [
          "app/client/(workspace)/profile/page.tsx"
        ],
        "scannedFiles": [
          "app/client/(workspace)/profile/page.tsx"
        ]
      }
    },
    {
      "surfaceId": "client-dashboard",
      "route": "/client",
      "mode": "source-scan",
      "compare": {
        "declared": [],
        "discovered": [],
        "aligned": [],
        "declaredOnly": [],
        "discoveredOnly": [],
        "inherited": [],
        "status": "aligned"
      },
      "evidence": {
        "entryFiles": [
          "app/client/(workspace)/page.tsx"
        ],
        "scannedFiles": [
          "app/client/(workspace)/page.tsx"
        ]
      }
    },
    {
      "surfaceId": "client-acknowledgement",
      "route": "/client",
      "mode": "source-scan",
      "compare": {
        "declared": [],
        "discovered": [],
        "aligned": [],
        "declaredOnly": [],
        "discoveredOnly": [],
        "inherited": [],
        "status": "aligned"
      },
      "evidence": {
        "entryFiles": [
          "app/client/(workspace)/page.tsx"
        ],
        "scannedFiles": [
          "app/client/(workspace)/page.tsx"
        ]
      }
    },
    {
      "surfaceId": "client-declare",
      "route": "/client/declare/[id]",
      "mode": "source-scan",
      "compare": {
        "declared": [],
        "discovered": [],
        "aligned": [],
        "declaredOnly": [],
        "discoveredOnly": [],
        "inherited": [],
        "status": "aligned"
      },
      "evidence": {
        "entryFiles": [
          "app/client/(workspace)/declare/[assignmentId]/page.tsx",
          "app/client/(workspace)/declare/[assignmentId]/loading.tsx",
          "app/client/(workspace)/declare/[assignmentId]/not-found.tsx"
        ],
        "scannedFiles": [
          "app/client/(workspace)/declare/[assignmentId]/loading.tsx",
          "app/client/(workspace)/declare/[assignmentId]/not-found.tsx",
          "app/client/(workspace)/declare/[assignmentId]/page.tsx"
        ]
      }
    },
    {
      "surfaceId": "admin-dashboard",
      "route": "/dashboard",
      "mode": "source-scan",
      "compare": {
        "declared": [
          "action:createDraftSurveyAction",
          "action:deleteSurveyAction",
          "domain:clients",
          "domain:operator-dashboard-page",
          "domain:surveys"
        ],
        "discovered": [
          "action:createDraftSurveyAction",
          "action:deleteSurveyAction",
          "domain:clients",
          "domain:surveys"
        ],
        "aligned": [
          "action:createDraftSurveyAction",
          "action:deleteSurveyAction",
          "domain:clients",
          "domain:operator-dashboard-page",
          "domain:surveys"
        ],
        "declaredOnly": [],
        "discoveredOnly": [],
        "inherited": [
          "domain:operator-dashboard-page"
        ],
        "status": "aligned"
      },
      "evidence": {
        "entryFiles": [
          "app/dashboard/page.tsx",
          "app/dashboard/loading.tsx",
          "features/organization-admin/organization-admin-dashboard-page.ts",
          "features/organization-admin/organization-admin-dashboard-types.ts",
          "components-V2/platform-views/portal-views/organization-admin-declarations-dashboard.tsx",
          "components-V2/platform-views/portal-views/portal-declarations-datatable.tsx",
          "components-V2/platform-views/portal-views/portal-organization-admin-statistics-card.tsx",
          "components-V2/platform-views/portal-views/portal-declarations-table.tsx"
        ],
        "scannedFiles": [
          "app/dashboard/loading.tsx",
          "app/dashboard/page.tsx",
          "components-V2/platform-views/portal-views/organization-admin-declarations-dashboard.tsx",
          "components-V2/platform-views/portal-views/portal-declarations-datatable.tsx",
          "components-V2/platform-views/portal-views/portal-declarations-table.tsx",
          "components-V2/platform-views/portal-views/portal-organization-admin-statistics-card.tsx",
          "features/organization-admin/organization-admin-dashboard-page.ts",
          "features/organization-admin/organization-admin-dashboard-types.ts"
        ]
      }
    },
    {
      "surfaceId": "admin-declaration-detail",
      "route": "/dashboard/[declarationId]",
      "mode": "source-scan",
      "compare": {
        "declared": [
          "action:deleteSurveyAction",
          "action:regenerateInviteTokenAction",
          "action:requireAdminSession",
          "action:updateSurveyAction",
          "domain:auth",
          "domain:operator-declaration-detail",
          "domain:questions",
          "domain:survey-package",
          "domain:surveys"
        ],
        "discovered": [
          "action:deleteSurveyAction",
          "action:regenerateInviteTokenAction",
          "action:updateSurveyAction",
          "domain:auth",
          "domain:questions",
          "domain:survey-package",
          "domain:surveys"
        ],
        "aligned": [
          "action:deleteSurveyAction",
          "action:regenerateInviteTokenAction",
          "action:requireAdminSession",
          "action:updateSurveyAction",
          "domain:auth",
          "domain:operator-declaration-detail",
          "domain:questions",
          "domain:survey-package",
          "domain:surveys"
        ],
        "declaredOnly": [],
        "discoveredOnly": [],
        "inherited": [
          "action:requireAdminSession",
          "domain:operator-declaration-detail"
        ],
        "status": "aligned"
      },
      "evidence": {
        "entryFiles": [
          "app/dashboard/[declarationId]/page.tsx",
          "app/dashboard/[declarationId]/loading.tsx",
          "features/organization-admin/organization-admin-declaration-detail.tsx",
          "features/organization-admin/organization-admin-declaration-detail.logic.ts",
          "components-V2/platform-views/portal-views/organization-admin-declaration-detail.tsx",
          "components-V2/platform-views/portal-views/portal-declaration-submissions-table.tsx",
          "components-V2/platform-views/portal-views/portal-access-share-panel.tsx",
          "features/organization-admin/declaration-manage-form.tsx",
          "features/organization-admin/declaration-share-panel.tsx",
          "features/organization-admin/declaration-danger-zone.tsx",
          "features/organization-admin/declaration-delete-button.tsx",
          "features/organization-admin/secure-link-rotate-button.tsx",
          "features/organization-admin/submission-answers.tsx"
        ],
        "scannedFiles": [
          "app/dashboard/[declarationId]/loading.tsx",
          "app/dashboard/[declarationId]/page.tsx",
          "components-V2/platform-views/portal-views/organization-admin-declaration-detail.tsx",
          "components-V2/platform-views/portal-views/portal-access-share-panel.tsx",
          "components-V2/platform-views/portal-views/portal-declaration-submissions-table.tsx",
          "features/organization-admin/declaration-danger-zone.tsx",
          "features/organization-admin/declaration-delete-button.tsx",
          "features/organization-admin/declaration-manage-form.tsx",
          "features/organization-admin/declaration-share-panel.tsx",
          "features/organization-admin/organization-admin-declaration-detail.logic.ts",
          "features/organization-admin/organization-admin-declaration-detail.tsx",
          "features/organization-admin/secure-link-rotate-button.tsx",
          "features/organization-admin/submission-answers.tsx"
        ]
      }
    },
    {
      "surfaceId": "admin-clients",
      "route": "/dashboard/clients",
      "mode": "source-scan",
      "compare": {
        "declared": [
          "action:deleteClientAssignmentAction",
          "action:issueClientInviteAction",
          "action:removeClientRegistrationAction",
          "domain:clients",
          "domain:email",
          "domain:operator-clients-page",
          "domain:surveys"
        ],
        "discovered": [
          "action:deleteClientAssignmentAction",
          "action:issueClientInviteAction",
          "action:removeClientRegistrationAction",
          "domain:clients",
          "domain:email",
          "domain:surveys"
        ],
        "aligned": [
          "action:deleteClientAssignmentAction",
          "action:issueClientInviteAction",
          "action:removeClientRegistrationAction",
          "domain:clients",
          "domain:email",
          "domain:operator-clients-page",
          "domain:surveys"
        ],
        "declaredOnly": [],
        "discoveredOnly": [],
        "inherited": [
          "domain:operator-clients-page"
        ],
        "status": "aligned"
      },
      "evidence": {
        "entryFiles": [
          "app/dashboard/clients/page.tsx",
          "app/dashboard/clients/loading.tsx",
          "features/organization-admin/organization-admin-clients-page.ts",
          "features/organization-admin/organization-admin-clients-types.ts",
          "modules/identity/email/client-email-delivery.ts",
          "modules/identity/email/send-client-onboarding-email.ts",
          "components-V2/platform-views/portal-views/organization-admin-clients-list.tsx",
          "components-V2/platform-views/portal-views/portal-client-tables.tsx",
          "components-V2/platform-views/portal-views/portal-client-delete-buttons.tsx",
          "components-V2/platform-views/portal-views/portal-invite-client-link.tsx",
          "features/organization-admin/issue-client-invite-form.tsx"
        ],
        "scannedFiles": [
          "app/dashboard/clients/loading.tsx",
          "app/dashboard/clients/page.tsx",
          "components-V2/platform-views/portal-views/organization-admin-clients-list.tsx",
          "components-V2/platform-views/portal-views/portal-client-delete-buttons.tsx",
          "components-V2/platform-views/portal-views/portal-client-tables.tsx",
          "components-V2/platform-views/portal-views/portal-invite-client-link.tsx",
          "features/organization-admin/issue-client-invite-form.tsx",
          "features/organization-admin/organization-admin-clients-page.ts",
          "features/organization-admin/organization-admin-clients-types.ts",
          "modules/identity/email/client-email-delivery.ts",
          "modules/identity/email/send-client-onboarding-email.ts"
        ]
      }
    },
    {
      "surfaceId": "admin-issue-invite",
      "route": "/dashboard/clients (invite)",
      "mode": "source-scan",
      "compare": {
        "declared": [
          "action:issueClientInviteAction",
          "action:requireAdminSession",
          "auth:organization/invite-member"
        ],
        "discovered": [
          "action:issueClientInviteAction"
        ],
        "aligned": [
          "action:issueClientInviteAction",
          "action:requireAdminSession",
          "auth:organization/invite-member"
        ],
        "declaredOnly": [],
        "discoveredOnly": [],
        "inherited": [
          "action:requireAdminSession",
          "auth:organization/invite-member"
        ],
        "status": "aligned"
      },
      "evidence": {
        "entryFiles": [
          "features/organization-admin/issue-client-invite-form.tsx",
          "modules/identity/email/send-client-onboarding-email.ts"
        ],
        "scannedFiles": [
          "features/organization-admin/issue-client-invite-form.tsx",
          "modules/identity/email/send-client-onboarding-email.ts"
        ]
      }
    },
    {
      "surfaceId": "admin-create-declaration",
      "route": "/dashboard/[declarationId] (create)",
      "mode": "source-scan",
      "compare": {
        "declared": [
          "action:createDraftSurveyAction"
        ],
        "discovered": [
          "action:createDraftSurveyAction"
        ],
        "aligned": [
          "action:createDraftSurveyAction"
        ],
        "declaredOnly": [],
        "discoveredOnly": [],
        "inherited": [],
        "status": "aligned"
      },
      "evidence": {
        "entryFiles": [
          "components-V2/platform-views/portal-views/portal-create-declaration-button.tsx"
        ],
        "scannedFiles": [
          "components-V2/platform-views/portal-views/portal-create-declaration-button.tsx"
        ]
      }
    },
    {
      "surfaceId": "admin-access-share",
      "route": "/dashboard/[declarationId] (share)",
      "mode": "source-scan",
      "compare": {
        "declared": [
          "action:regenerateInviteTokenAction",
          "action:requireAdminSession",
          "domain:auth",
          "domain:surveys"
        ],
        "discovered": [
          "action:regenerateInviteTokenAction",
          "domain:auth",
          "domain:surveys"
        ],
        "aligned": [
          "action:regenerateInviteTokenAction",
          "action:requireAdminSession",
          "domain:auth",
          "domain:surveys"
        ],
        "declaredOnly": [],
        "discoveredOnly": [],
        "inherited": [
          "action:requireAdminSession"
        ],
        "status": "aligned"
      },
      "evidence": {
        "entryFiles": [
          "features/organization-admin/declaration-share-panel.tsx",
          "features/organization-admin/secure-link-rotate-button.tsx",
          "components-V2/platform-views/portal-views/portal-access-share-panel.tsx",
          "modules/declarations/domain/declaration-share-links.ts"
        ],
        "scannedFiles": [
          "components-V2/platform-views/portal-views/portal-access-share-panel.tsx",
          "features/organization-admin/declaration-share-panel.tsx",
          "features/organization-admin/secure-link-rotate-button.tsx",
          "modules/declarations/domain/declaration-share-links.ts"
        ]
      }
    },
    {
      "surfaceId": "public-survey-link",
      "route": "/survey/[slug]",
      "mode": "source-scan",
      "compare": {
        "declared": [
          "domain:auth",
          "domain:clients",
          "domain:open-link-entry",
          "domain:surveys"
        ],
        "discovered": [
          "domain:auth",
          "domain:clients",
          "domain:surveys"
        ],
        "aligned": [
          "domain:auth",
          "domain:clients",
          "domain:open-link-entry",
          "domain:surveys"
        ],
        "declaredOnly": [],
        "discoveredOnly": [],
        "inherited": [
          "domain:open-link-entry"
        ],
        "status": "aligned"
      },
      "evidence": {
        "entryFiles": [
          "app/survey/[slug]/page.tsx",
          "features/auth/entry/open-link-entry.ts",
          "features/auth/public-link-page.ts",
          "features/auth/public-link-routing.ts"
        ],
        "scannedFiles": [
          "app/survey/[slug]/page.tsx",
          "features/auth/entry/open-link-entry.ts",
          "features/auth/public-link-page.ts",
          "features/auth/public-link-routing.ts"
        ]
      }
    },
    {
      "surfaceId": "public-secure-link",
      "route": "/f/[token]",
      "mode": "source-scan",
      "compare": {
        "declared": [
          "domain:auth",
          "domain:clients",
          "domain:secure-link-entry",
          "domain:surveys"
        ],
        "discovered": [
          "domain:auth",
          "domain:clients",
          "domain:surveys"
        ],
        "aligned": [
          "domain:auth",
          "domain:clients",
          "domain:secure-link-entry",
          "domain:surveys"
        ],
        "declaredOnly": [],
        "discoveredOnly": [],
        "inherited": [
          "domain:secure-link-entry"
        ],
        "status": "aligned"
      },
      "evidence": {
        "entryFiles": [
          "app/f/[token]/page.tsx",
          "features/auth/entry/secure-link-entry.ts",
          "features/auth/public-link-page.ts",
          "features/auth/public-link-routing.ts"
        ],
        "scannedFiles": [
          "app/f/[token]/page.tsx",
          "features/auth/entry/secure-link-entry.ts",
          "features/auth/public-link-page.ts",
          "features/auth/public-link-routing.ts"
        ]
      }
    },
    {
      "surfaceId": "org-login",
      "route": "/org/login",
      "mode": "auth-pathname",
      "compare": {
        "declared": [
          "auth:sign-in/email"
        ],
        "discovered": [
          "auth:sign-in/email"
        ],
        "aligned": [
          "auth:sign-in/email"
        ],
        "declaredOnly": [],
        "discoveredOnly": [],
        "inherited": [],
        "status": "aligned"
      },
      "evidence": {
        "entryFiles": [
          "features/auth/entry/org-sign-in-entry.ts",
          "modules/platform/routing/portal-routes.ts"
        ],
        "scannedFiles": [
          "features/auth/entry/org-sign-in-entry.ts",
          "modules/platform/routing/portal-routes.ts"
        ]
      }
    },
    {
      "surfaceId": "shell-dashboard",
      "route": "/dashboard layout",
      "mode": "source-scan",
      "compare": {
        "declared": [
          "domain:auth"
        ],
        "discovered": [
          "domain:auth"
        ],
        "aligned": [
          "domain:auth"
        ],
        "declaredOnly": [],
        "discoveredOnly": [],
        "inherited": [],
        "status": "aligned"
      },
      "evidence": {
        "entryFiles": [
          "app/dashboard/layout.tsx",
          "components-V2/platform-components/AdminCnShell.tsx",
          "components-V2/platform-components/layout/PagesLayout.tsx",
          "components-V2/platform-config/navConfig.tsx",
          "components-V2/platform-config/themeConfig.ts"
        ],
        "scannedFiles": [
          "app/dashboard/layout.tsx",
          "components-V2/platform-components/AdminCnShell.tsx",
          "components-V2/platform-components/layout/PagesLayout.tsx",
          "components-V2/platform-config/navConfig.tsx",
          "components-V2/platform-config/themeConfig.ts"
        ]
      }
    },
    {
      "surfaceId": "client-preview-banner",
      "route": "/client (preview mode)",
      "mode": "source-scan",
      "compare": {
        "declared": [],
        "discovered": [],
        "aligned": [],
        "declaredOnly": [],
        "discoveredOnly": [],
        "inherited": [],
        "status": "aligned"
      },
      "evidence": {
        "entryFiles": [
          "app/client/(workspace)/layout.tsx"
        ],
        "scannedFiles": [
          "app/client/(workspace)/layout.tsx"
        ]
      }
    }
  ],
  "actions": [
    {
      "actionId": "action:requireClientSession",
      "file": "modules/identity/auth/session.ts",
      "compare": {
        "declared": [
          "domain:auth"
        ],
        "discovered": [
          "domain:audit",
          "domain:auth",
          "domain:preview-client"
        ],
        "aligned": [
          "domain:auth"
        ],
        "declaredOnly": [],
        "discoveredOnly": [
          "domain:audit",
          "domain:preview-client"
        ],
        "inherited": [],
        "status": "aligned"
      }
    },
    {
      "actionId": "action:requireAdminSession",
      "file": "modules/identity/auth/session.ts",
      "compare": {
        "declared": [
          "domain:auth"
        ],
        "discovered": [
          "domain:audit",
          "domain:auth",
          "domain:preview-client"
        ],
        "aligned": [
          "domain:auth"
        ],
        "declaredOnly": [],
        "discoveredOnly": [
          "domain:audit",
          "domain:preview-client"
        ],
        "inherited": [],
        "status": "aligned"
      }
    },
    {
      "actionId": "action:requireAccountSession",
      "file": "modules/identity/account-session.ts",
      "compare": {
        "declared": [
          "domain:auth",
          "domain:clients"
        ],
        "discovered": [
          "domain:auth",
          "domain:clients"
        ],
        "aligned": [
          "domain:auth",
          "domain:clients"
        ],
        "declaredOnly": [],
        "discoveredOnly": [],
        "inherited": [],
        "status": "aligned"
      }
    },
    {
      "actionId": "action:saveClientOnboardingAction",
      "file": "app/actions/client.ts",
      "compare": {
        "declared": [
          "domain:audit",
          "domain:auth",
          "domain:clients"
        ],
        "discovered": [
          "domain:audit",
          "domain:auth",
          "domain:client-onboarding",
          "domain:clients",
          "domain:email",
          "domain:questions",
          "domain:surveys"
        ],
        "aligned": [
          "domain:audit",
          "domain:auth",
          "domain:clients"
        ],
        "declaredOnly": [],
        "discoveredOnly": [
          "domain:client-onboarding",
          "domain:email",
          "domain:questions",
          "domain:surveys"
        ],
        "inherited": [],
        "status": "aligned"
      }
    },
    {
      "actionId": "action:issueClientInviteAction",
      "file": "app/actions/client.ts",
      "compare": {
        "declared": [
          "domain:audit",
          "domain:auth",
          "domain:clients",
          "domain:email"
        ],
        "discovered": [
          "domain:audit",
          "domain:auth",
          "domain:client-onboarding",
          "domain:clients",
          "domain:email",
          "domain:questions",
          "domain:surveys"
        ],
        "aligned": [
          "domain:audit",
          "domain:auth",
          "domain:clients",
          "domain:email"
        ],
        "declaredOnly": [],
        "discoveredOnly": [
          "domain:client-onboarding",
          "domain:questions",
          "domain:surveys"
        ],
        "inherited": [],
        "status": "aligned"
      }
    },
    {
      "actionId": "action:removeClientRegistrationAction",
      "file": "app/actions/client.ts",
      "compare": {
        "declared": [
          "domain:audit",
          "domain:auth",
          "domain:clients"
        ],
        "discovered": [
          "domain:audit",
          "domain:auth",
          "domain:client-onboarding",
          "domain:clients",
          "domain:email",
          "domain:questions",
          "domain:surveys"
        ],
        "aligned": [
          "domain:audit",
          "domain:auth",
          "domain:clients"
        ],
        "declaredOnly": [],
        "discoveredOnly": [
          "domain:client-onboarding",
          "domain:email",
          "domain:questions",
          "domain:surveys"
        ],
        "inherited": [],
        "status": "aligned"
      }
    },
    {
      "actionId": "action:submitClientDeclarationAction",
      "file": "app/actions/client.ts",
      "compare": {
        "declared": [
          "domain:audit",
          "domain:clients",
          "domain:questions",
          "domain:surveys"
        ],
        "discovered": [
          "domain:audit",
          "domain:auth",
          "domain:client-onboarding",
          "domain:clients",
          "domain:email",
          "domain:questions",
          "domain:surveys"
        ],
        "aligned": [
          "domain:audit",
          "domain:clients",
          "domain:questions",
          "domain:surveys"
        ],
        "declaredOnly": [],
        "discoveredOnly": [
          "domain:auth",
          "domain:client-onboarding",
          "domain:email"
        ],
        "inherited": [],
        "status": "aligned"
      }
    },
    {
      "actionId": "action:saveClientDeclarationDraftAction",
      "file": "app/actions/client.ts",
      "compare": {
        "declared": [
          "domain:clients",
          "domain:questions",
          "domain:surveys"
        ],
        "discovered": [
          "domain:audit",
          "domain:auth",
          "domain:client-onboarding",
          "domain:clients",
          "domain:email",
          "domain:questions",
          "domain:surveys"
        ],
        "aligned": [
          "domain:clients",
          "domain:questions",
          "domain:surveys"
        ],
        "declaredOnly": [],
        "discoveredOnly": [
          "domain:audit",
          "domain:auth",
          "domain:client-onboarding",
          "domain:email"
        ],
        "inherited": [],
        "status": "aligned"
      }
    },
    {
      "actionId": "action:writeClientDeclarationDraftApi",
      "file": "modules/platform/api/client-declaration-draft-route.ts",
      "compare": {
        "declared": [
          "domain:auth",
          "domain:clients"
        ],
        "discovered": [
          "domain:auth",
          "domain:clients"
        ],
        "aligned": [
          "domain:auth",
          "domain:clients"
        ],
        "declaredOnly": [],
        "discoveredOnly": [],
        "inherited": [],
        "status": "aligned"
      }
    },
    {
      "actionId": "action:deleteClientAssignmentAction",
      "file": "app/actions/client.ts",
      "compare": {
        "declared": [
          "domain:audit",
          "domain:clients"
        ],
        "discovered": [
          "domain:audit",
          "domain:auth",
          "domain:client-onboarding",
          "domain:clients",
          "domain:email",
          "domain:questions",
          "domain:surveys"
        ],
        "aligned": [
          "domain:audit",
          "domain:clients"
        ],
        "declaredOnly": [],
        "discoveredOnly": [
          "domain:auth",
          "domain:client-onboarding",
          "domain:email",
          "domain:questions",
          "domain:surveys"
        ],
        "inherited": [],
        "status": "aligned"
      }
    },
    {
      "actionId": "action:acknowledgeClientPortalAction",
      "file": "app/actions/client.ts",
      "compare": {
        "declared": [
          "domain:audit",
          "domain:clients"
        ],
        "discovered": [
          "domain:audit",
          "domain:auth",
          "domain:client-onboarding",
          "domain:clients",
          "domain:email",
          "domain:questions",
          "domain:surveys"
        ],
        "aligned": [
          "domain:audit",
          "domain:clients"
        ],
        "declaredOnly": [],
        "discoveredOnly": [
          "domain:auth",
          "domain:client-onboarding",
          "domain:email",
          "domain:questions",
          "domain:surveys"
        ],
        "inherited": [],
        "status": "aligned"
      }
    },
    {
      "actionId": "action:createDraftSurveyAction",
      "file": "app/actions/surveys.ts",
      "compare": {
        "declared": [
          "domain:audit",
          "domain:surveys"
        ],
        "discovered": [
          "domain:audit",
          "domain:auth",
          "domain:clients",
          "domain:questions",
          "domain:survey-package",
          "domain:surveys"
        ],
        "aligned": [
          "domain:audit",
          "domain:surveys"
        ],
        "declaredOnly": [],
        "discoveredOnly": [
          "domain:auth",
          "domain:clients",
          "domain:questions",
          "domain:survey-package"
        ],
        "inherited": [],
        "status": "aligned"
      }
    },
    {
      "actionId": "action:updateSurveyAction",
      "file": "app/actions/surveys.ts",
      "compare": {
        "declared": [
          "domain:audit",
          "domain:questions",
          "domain:surveys"
        ],
        "discovered": [
          "domain:audit",
          "domain:auth",
          "domain:clients",
          "domain:questions",
          "domain:survey-package",
          "domain:surveys"
        ],
        "aligned": [
          "domain:audit",
          "domain:questions",
          "domain:surveys"
        ],
        "declaredOnly": [],
        "discoveredOnly": [
          "domain:auth",
          "domain:clients",
          "domain:survey-package"
        ],
        "inherited": [],
        "status": "aligned"
      }
    },
    {
      "actionId": "action:deleteSurveyAction",
      "file": "app/actions/surveys.ts",
      "compare": {
        "declared": [
          "domain:audit",
          "domain:surveys"
        ],
        "discovered": [
          "domain:audit",
          "domain:auth",
          "domain:clients",
          "domain:questions",
          "domain:survey-package",
          "domain:surveys"
        ],
        "aligned": [
          "domain:audit",
          "domain:surveys"
        ],
        "declaredOnly": [],
        "discoveredOnly": [
          "domain:auth",
          "domain:clients",
          "domain:questions",
          "domain:survey-package"
        ],
        "inherited": [],
        "status": "aligned"
      }
    },
    {
      "actionId": "action:exportSurveyPackageAction",
      "file": "app/actions/surveys.ts",
      "compare": {
        "declared": [
          "domain:survey-package",
          "domain:surveys"
        ],
        "discovered": [
          "domain:audit",
          "domain:auth",
          "domain:clients",
          "domain:questions",
          "domain:survey-package",
          "domain:surveys"
        ],
        "aligned": [
          "domain:survey-package",
          "domain:surveys"
        ],
        "declaredOnly": [],
        "discoveredOnly": [
          "domain:audit",
          "domain:auth",
          "domain:clients",
          "domain:questions"
        ],
        "inherited": [],
        "status": "aligned"
      }
    },
    {
      "actionId": "action:importSurveyPackageAction",
      "file": "app/actions/surveys.ts",
      "compare": {
        "declared": [
          "domain:audit",
          "domain:questions",
          "domain:survey-package",
          "domain:surveys"
        ],
        "discovered": [
          "domain:audit",
          "domain:auth",
          "domain:clients",
          "domain:questions",
          "domain:survey-package",
          "domain:surveys"
        ],
        "aligned": [
          "domain:audit",
          "domain:questions",
          "domain:survey-package",
          "domain:surveys"
        ],
        "declaredOnly": [],
        "discoveredOnly": [
          "domain:auth",
          "domain:clients"
        ],
        "inherited": [],
        "status": "aligned"
      }
    },
    {
      "actionId": "action:submitSurveyResponseAction",
      "file": "app/actions/surveys.ts",
      "compare": {
        "declared": [
          "domain:audit",
          "domain:clients",
          "domain:questions",
          "domain:surveys"
        ],
        "discovered": [
          "domain:audit",
          "domain:auth",
          "domain:clients",
          "domain:questions",
          "domain:survey-package",
          "domain:surveys"
        ],
        "aligned": [
          "domain:audit",
          "domain:clients",
          "domain:questions",
          "domain:surveys"
        ],
        "declaredOnly": [],
        "discoveredOnly": [
          "domain:auth",
          "domain:survey-package"
        ],
        "inherited": [],
        "status": "aligned"
      }
    },
    {
      "actionId": "action:registerEvidenceAction",
      "file": "app/actions/declarations.ts",
      "compare": {
        "declared": [
          "domain:audit",
          "domain:clients",
          "domain:questions",
          "domain:surveys"
        ],
        "discovered": [
          "domain:audit",
          "domain:auth",
          "domain:clients",
          "domain:questions",
          "domain:surveys"
        ],
        "aligned": [
          "domain:audit",
          "domain:clients",
          "domain:questions",
          "domain:surveys"
        ],
        "declaredOnly": [],
        "discoveredOnly": [
          "domain:auth"
        ],
        "inherited": [],
        "status": "aligned"
      }
    },
    {
      "actionId": "action:regenerateInviteTokenAction",
      "file": "app/actions/surveys.ts",
      "compare": {
        "declared": [
          "domain:audit",
          "domain:surveys"
        ],
        "discovered": [
          "domain:audit",
          "domain:auth",
          "domain:clients",
          "domain:questions",
          "domain:survey-package",
          "domain:surveys"
        ],
        "aligned": [
          "domain:audit",
          "domain:surveys"
        ],
        "declaredOnly": [],
        "discoveredOnly": [
          "domain:auth",
          "domain:clients",
          "domain:questions",
          "domain:survey-package"
        ],
        "inherited": [],
        "status": "aligned"
      }
    },
    {
      "actionId": "action:startClientPreviewAction",
      "file": "app/actions/admin.ts",
      "compare": {
        "declared": [
          "domain:audit",
          "domain:preview-client"
        ],
        "discovered": [
          "domain:audit",
          "domain:auth",
          "domain:preview-client"
        ],
        "aligned": [
          "domain:audit",
          "domain:preview-client"
        ],
        "declaredOnly": [],
        "discoveredOnly": [
          "domain:auth"
        ],
        "inherited": [],
        "status": "aligned"
      }
    },
    {
      "actionId": "action:exitClientPreviewAction",
      "file": "app/actions/admin.ts",
      "compare": {
        "declared": [
          "domain:audit",
          "domain:preview-client"
        ],
        "discovered": [
          "domain:audit",
          "domain:auth",
          "domain:preview-client"
        ],
        "aligned": [
          "domain:audit",
          "domain:preview-client"
        ],
        "declaredOnly": [],
        "discoveredOnly": [
          "domain:auth"
        ],
        "inherited": [],
        "status": "aligned"
      }
    },
    {
      "actionId": "action:setOrganizationUserRoleAction",
      "file": "app/actions/admin.ts",
      "compare": {
        "declared": [
          "domain:audit",
          "domain:auth"
        ],
        "discovered": [
          "domain:audit",
          "domain:auth",
          "domain:preview-client"
        ],
        "aligned": [
          "domain:audit",
          "domain:auth"
        ],
        "declaredOnly": [],
        "discoveredOnly": [
          "domain:preview-client"
        ],
        "inherited": [],
        "status": "aligned"
      }
    },
    {
      "actionId": "action:banOrganizationUserAction",
      "file": "app/actions/admin.ts",
      "compare": {
        "declared": [
          "domain:audit",
          "domain:auth"
        ],
        "discovered": [
          "domain:audit",
          "domain:auth",
          "domain:preview-client"
        ],
        "aligned": [
          "domain:audit",
          "domain:auth"
        ],
        "declaredOnly": [],
        "discoveredOnly": [
          "domain:preview-client"
        ],
        "inherited": [],
        "status": "aligned"
      }
    },
    {
      "actionId": "action:unbanOrganizationUserAction",
      "file": "app/actions/admin.ts",
      "compare": {
        "declared": [
          "domain:audit",
          "domain:auth"
        ],
        "discovered": [
          "domain:audit",
          "domain:auth",
          "domain:preview-client"
        ],
        "aligned": [
          "domain:audit",
          "domain:auth"
        ],
        "declaredOnly": [],
        "discoveredOnly": [
          "domain:preview-client"
        ],
        "inherited": [],
        "status": "aligned"
      }
    },
    {
      "actionId": "action:createOrganizationUserAction",
      "file": "app/actions/admin.ts",
      "compare": {
        "declared": [
          "domain:audit",
          "domain:auth"
        ],
        "discovered": [
          "domain:audit",
          "domain:auth",
          "domain:preview-client"
        ],
        "aligned": [
          "domain:audit",
          "domain:auth"
        ],
        "declaredOnly": [],
        "discoveredOnly": [
          "domain:preview-client"
        ],
        "inherited": [],
        "status": "aligned"
      }
    },
    {
      "actionId": "action:importOrganizationUsersAction",
      "file": "app/actions/admin.ts",
      "compare": {
        "declared": [
          "domain:audit",
          "domain:auth"
        ],
        "discovered": [
          "domain:audit",
          "domain:auth",
          "domain:preview-client"
        ],
        "aligned": [
          "domain:audit",
          "domain:auth"
        ],
        "declaredOnly": [],
        "discoveredOnly": [
          "domain:preview-client"
        ],
        "inherited": [],
        "status": "aligned"
      }
    },
    {
      "actionId": "action:updateOrganizationUserAction",
      "file": "app/actions/admin.ts",
      "compare": {
        "declared": [
          "domain:audit",
          "domain:auth"
        ],
        "discovered": [
          "domain:audit",
          "domain:auth",
          "domain:preview-client"
        ],
        "aligned": [
          "domain:audit",
          "domain:auth"
        ],
        "declaredOnly": [],
        "discoveredOnly": [
          "domain:preview-client"
        ],
        "inherited": [],
        "status": "aligned"
      }
    },
    {
      "actionId": "action:setOrganizationUserPasswordAction",
      "file": "app/actions/admin.ts",
      "compare": {
        "declared": [
          "domain:audit",
          "domain:auth"
        ],
        "discovered": [
          "domain:audit",
          "domain:auth",
          "domain:preview-client"
        ],
        "aligned": [
          "domain:audit",
          "domain:auth"
        ],
        "declaredOnly": [],
        "discoveredOnly": [
          "domain:preview-client"
        ],
        "inherited": [],
        "status": "aligned"
      }
    },
    {
      "actionId": "action:removeOrganizationUserAction",
      "file": "app/actions/admin.ts",
      "compare": {
        "declared": [
          "domain:audit",
          "domain:auth"
        ],
        "discovered": [
          "domain:audit",
          "domain:auth",
          "domain:preview-client"
        ],
        "aligned": [
          "domain:audit",
          "domain:auth"
        ],
        "declaredOnly": [],
        "discoveredOnly": [
          "domain:preview-client"
        ],
        "inherited": [],
        "status": "aligned"
      }
    },
    {
      "actionId": "action:removeOrganizationUsersAction",
      "file": "app/actions/admin.ts",
      "compare": {
        "declared": [
          "domain:audit",
          "domain:auth"
        ],
        "discovered": [
          "domain:audit",
          "domain:auth",
          "domain:preview-client"
        ],
        "aligned": [
          "domain:audit",
          "domain:auth"
        ],
        "declaredOnly": [],
        "discoveredOnly": [
          "domain:preview-client"
        ],
        "inherited": [],
        "status": "aligned"
      }
    },
    {
      "actionId": "action:banOrganizationUsersAction",
      "file": "app/actions/admin.ts",
      "compare": {
        "declared": [
          "domain:audit",
          "domain:auth"
        ],
        "discovered": [
          "domain:audit",
          "domain:auth",
          "domain:preview-client"
        ],
        "aligned": [
          "domain:audit",
          "domain:auth"
        ],
        "declaredOnly": [],
        "discoveredOnly": [
          "domain:preview-client"
        ],
        "inherited": [],
        "status": "aligned"
      }
    },
    {
      "actionId": "action:revokeOrganizationUserSessionsAction",
      "file": "app/actions/admin.ts",
      "compare": {
        "declared": [
          "domain:audit",
          "domain:auth"
        ],
        "discovered": [
          "domain:audit",
          "domain:auth",
          "domain:preview-client"
        ],
        "aligned": [
          "domain:audit",
          "domain:auth"
        ],
        "declaredOnly": [],
        "discoveredOnly": [
          "domain:preview-client"
        ],
        "inherited": [],
        "status": "aligned"
      }
    },
    {
      "actionId": "action:createPlatformRoleAction",
      "file": "app/actions/admin.ts",
      "compare": {
        "declared": [
          "domain:audit",
          "domain:auth"
        ],
        "discovered": [
          "domain:audit",
          "domain:auth",
          "domain:preview-client"
        ],
        "aligned": [
          "domain:audit",
          "domain:auth"
        ],
        "declaredOnly": [],
        "discoveredOnly": [
          "domain:preview-client"
        ],
        "inherited": [],
        "status": "aligned"
      }
    },
    {
      "actionId": "action:updatePlatformRoleAction",
      "file": "app/actions/admin.ts",
      "compare": {
        "declared": [
          "domain:audit",
          "domain:auth"
        ],
        "discovered": [
          "domain:audit",
          "domain:auth",
          "domain:preview-client"
        ],
        "aligned": [
          "domain:audit",
          "domain:auth"
        ],
        "declaredOnly": [],
        "discoveredOnly": [
          "domain:preview-client"
        ],
        "inherited": [],
        "status": "aligned"
      }
    },
    {
      "actionId": "action:deletePlatformRoleAction",
      "file": "app/actions/admin.ts",
      "compare": {
        "declared": [
          "domain:audit",
          "domain:auth"
        ],
        "discovered": [
          "domain:audit",
          "domain:auth",
          "domain:preview-client"
        ],
        "aligned": [
          "domain:audit",
          "domain:auth"
        ],
        "declaredOnly": [],
        "discoveredOnly": [
          "domain:preview-client"
        ],
        "inherited": [],
        "status": "aligned"
      }
    },
    {
      "actionId": "action:setPlatformRolePermissionAction",
      "file": "app/actions/admin.ts",
      "compare": {
        "declared": [
          "domain:audit",
          "domain:auth"
        ],
        "discovered": [
          "domain:audit",
          "domain:auth",
          "domain:preview-client"
        ],
        "aligned": [
          "domain:audit",
          "domain:auth"
        ],
        "declaredOnly": [],
        "discoveredOnly": [
          "domain:preview-client"
        ],
        "inherited": [],
        "status": "aligned"
      }
    },
    {
      "actionId": "action:assignPlatformRoleAction",
      "file": "app/actions/admin.ts",
      "compare": {
        "declared": [
          "domain:audit",
          "domain:auth"
        ],
        "discovered": [
          "domain:audit",
          "domain:auth",
          "domain:preview-client"
        ],
        "aligned": [
          "domain:audit",
          "domain:auth"
        ],
        "declaredOnly": [],
        "discoveredOnly": [
          "domain:preview-client"
        ],
        "inherited": [],
        "status": "aligned"
      }
    },
    {
      "actionId": "action:revokePlatformRoleAssignmentAction",
      "file": "app/actions/admin.ts",
      "compare": {
        "declared": [
          "domain:audit",
          "domain:auth"
        ],
        "discovered": [
          "domain:audit",
          "domain:auth",
          "domain:preview-client"
        ],
        "aligned": [
          "domain:audit",
          "domain:auth"
        ],
        "declaredOnly": [],
        "discoveredOnly": [
          "domain:preview-client"
        ],
        "inherited": [],
        "status": "aligned"
      }
    }
  ]
}
